[
  {
    "name": "Rui",
    "artist": "Meme50",
    "image": "https://pbs.twimg.com/media/FuMcYavaEAA-fiW?format=jpg&name=large",
    "link": "https://pbs.twimg.com/media/FuMcYavaEAA-fiW?format=jpg&name=large",
    "age": "16",
    "series": "Zubopuri",
    "race": "Human"
  },
  {
    "name": "Mokoko",
    "artist": "Meme50",
    "image": "https://pbs.twimg.com/media/D-UBGUaU4AUVK2o?format=jpg&name=medium",
    "link": "https://pbs.twimg.com/media/D-UBGUaU4AUVK2o?format=jpg&name=medium",
    "series": "Hitozuma Haramu",
    "race": "Human"
  },
  {
    "name": "Toa",
    "realName": "Sudou Toa",
    "artist": "Meme50",
    "image": "./image/toa.jpg",
    "link": "https://pbs.twimg.com/media/GL04btnaAAAjr54?format=jpg&name=large",
    "age": "16",
    "series": "Okane Daisuki",
    "race": "Human"
  },
  {
    "name": "Haru",
    "realName": "Arai Miharu",
    "artist": "Meme50",
    "image": "https://pbs.twimg.com/media/GCkh2SObYAAewYi?format=jpg&name=large",
    "link": "https://pbs.twimg.com/media/GCkh2SObYAAewYi?format=jpg&name=large",
    "age": "16",
    "series": "Miharu no Hajimete",
    "race": "Human"
  },
  {
    "name": "Ikuyo Hoshizora",
    "artist": "Meme50",
    "image": "https://m3.hentairox.com/010/pjqg6u71ew/1.jpg",
    "link": "https://m3.hentairox.com/010/pjqg6u71ew/1.jpg",
    "age": "40",
    "series": "Smile Prescure!",
    "race": "Human"
  }
]
